devapi/__init__.py
devapi-0.0.0.dist-info/LICENSE
devapi-0.0.0.dist-info/METADATA
devapi-0.0.0.dist-info/WHEEL
devapi-0.0.0.dist-info/RECORD
