Metadata-Version: 2.1
Name: devapi
Version: 0.0.0
Summary: coming soon
Author: zhangshulin
Author-email: zhangslwork@yeah.net
Requires-Python: >=3.12,<4.0
Classifier: Programming Language :: Python :: 3
Classifier: Programming Language :: Python :: 3.12
Classifier: Programming Language :: Python :: 3.13
